calculater/__init__.py
calculater/add.py
lyp_awesome-0.0.2.dist-info/METADATA
lyp_awesome-0.0.2.dist-info/WHEEL
lyp_awesome-0.0.2.dist-info/top_level.txt
lyp_awesome-0.0.2.dist-info/RECORD
