Metadata-Version: 2.4
Name: lyp-awesome
Version: 0.0.2
Summary: valar for morghulis
Author: LYP
Author-email: liuyinpeng@buaa.edu.cn
Requires-Python: >=3.9
Dynamic: author
Dynamic: author-email
Dynamic: description
Dynamic: description-content-type
Dynamic: requires-python
Dynamic: summary
